{
  "dashboard": {
    "title": "Resource Usage Overview",
    "uid": "resource-usage-overview",
    "version": 1,
    "timezone": "browser",
    "editable": true,
    "refresh": "30s",
    "time": {
      "from": "now-1h",
      "to": "now"
    },
    "panels": [
      {
        "id": 1,
        "title": "CPU Usage by Node",
        "type": "timeseries",
        "gridPos": {"x": 0, "y": 0, "w": 12, "h": 8},
        "targets": [
          {
            "expr": "100 - (avg by(instance) (irate(node_cpu_seconds_total{mode=\"idle\"}[5m])) * 100)",
            "legendFormat": "{{instance}}",
            "refId": "A"
          }
        ],
        "fieldConfig": {
          "defaults": {
            "unit": "percent",
            "max": 100,
            "custom": {
              "drawStyle": "line",
              "fillOpacity": 20
            },
            "thresholds": {
              "mode": "absolute",
              "steps": [
                {"value": 0, "color": "green"},
                {"value": 70, "color": "yellow"},
                {"value": 85, "color": "red"}
              ]
            }
          }
        }
      },
      {
        "id": 2,
        "title": "Memory Usage by Node",
        "type": "timeseries",
        "gridPos": {"x": 12, "y": 0, "w": 12, "h": 8},
        "targets": [
          {
            "expr": "(1 - (node_memory_MemAvailable_bytes / node_memory_MemTotal_bytes)) * 100",
            "legendFormat": "{{instance}}",
            "refId": "A"
          }
        ],
        "fieldConfig": {
          "defaults": {
            "unit": "percent",
            "max": 100,
            "thresholds": {
              "mode": "absolute",
              "steps": [
                {"value": 0, "color": "green"},
                {"value": 70, "color": "yellow"},
                {"value": 85, "color": "red"}
              ]
            }
          }
        }
      },
      {
        "id": 3,
        "title": "Disk Usage",
        "type": "gauge",
        "gridPos": {"x": 0, "y": 8, "w": 8, "h": 6},
        "targets": [
          {
            "expr": "(1 - (node_filesystem_avail_bytes{mountpoint=\"/\"} / node_filesystem_size_bytes{mountpoint=\"/\"})) * 100",
            "legendFormat": "{{instance}}",
            "refId": "A"
          }
        ],
        "fieldConfig": {
          "defaults": {
            "unit": "percent",
            "max": 100,
            "thresholds": {
              "mode": "absolute",
              "steps": [
                {"value": 0, "color": "green"},
                {"value": 70, "color": "yellow"},
                {"value": 85, "color": "red"}
              ]
            }
          }
        }
      },
      {
        "id": 4,
        "title": "Network Traffic",
        "type": "timeseries",
        "gridPos": {"x": 8, "y": 8, "w": 16, "h": 6},
        "targets": [
          {
            "expr": "rate(node_network_receive_bytes_total{device!=\"lo\"}[5m])",
            "legendFormat": "RX {{instance}}",
            "refId": "A"
          },
          {
            "expr": "rate(node_network_transmit_bytes_total{device!=\"lo\"}[5m])",
            "legendFormat": "TX {{instance}}",
            "refId": "B"
          }
        ],
        "fieldConfig": {
          "defaults": {
            "unit": "Bps"
          }
        }
      },
      {
        "id": 5,
        "title": "Container CPU Usage",
        "type": "timeseries",
        "gridPos": {"x": 0, "y": 14, "w": 12, "h": 8},
        "targets": [
          {
            "expr": "sum(rate(container_cpu_usage_seconds_total{container!=\"\"}[5m])) by (pod, namespace)",
            "legendFormat": "{{namespace}}/{{pod}}",
            "refId": "A"
          }
        ],
        "fieldConfig": {
          "defaults": {
            "unit": "percentunit"
          }
        }
      },
      {
        "id": 6,
        "title": "Container Memory Usage",
        "type": "timeseries",
        "gridPos": {"x": 12, "y": 14, "w": 12, "h": 8},
        "targets": [
          {
            "expr": "sum(container_memory_working_set_bytes{container!=\"\"}) by (pod, namespace) / sum(container_spec_memory_limit_bytes{container!=\"\"}) by (pod, namespace)",
            "legendFormat": "{{namespace}}/{{pod}}",
            "refId": "A"
          }
        ],
        "fieldConfig": {
          "defaults": {
            "unit": "percentunit"
          }
        }
      },
      {
        "id": 7,
        "title": "Disk I/O",
        "type": "timeseries",
        "gridPos": {"x": 0, "y": 22, "w": 12, "h": 8},
        "targets": [
          {
            "expr": "rate(node_disk_read_bytes_total[5m])",
            "legendFormat": "Read {{instance}}",
            "refId": "A"
          },
          {
            "expr": "rate(node_disk_written_bytes_total[5m])",
            "legendFormat": "Write {{instance}}",
            "refId": "B"
          }
        ],
        "fieldConfig": {
          "defaults": {
            "unit": "Bps"
          }
        }
      },
      {
        "id": 8,
        "title": "Load Average",
        "type": "timeseries",
        "gridPos": {"x": 12, "y": 22, "w": 12, "h": 8},
        "targets": [
          {
            "expr": "node_load1",
            "legendFormat": "1m {{instance}}",
            "refId": "A"
          },
          {
            "expr": "node_load5",
            "legendFormat": "5m {{instance}}",
            "refId": "B"
          },
          {
            "expr": "node_load15",
            "legendFormat": "15m {{instance}}",
            "refId": "C"
          }
        ]
      }
    ]
  }
}
